[{"name":"Spain","topLevelDomain":[".es"],"alpha2Code":"ES","alpha3Code":"ESP","callingCodes":["34"],"capital":"Madrid","altSpellings":["ES","Kingdom of Spain","Reino de España"],"region":"Europe","subregion":"Southern Europe","population":46438422,"latlng":[40.0,-4.0],"demonym":"Spanish","area":505992.0,"gini":34.7,"timezones":["UTC","UTC+01:00"],"borders":["AND","FRA","GIB","PRT","MAR"],"nativeName":"España","numericCode":"724","currencies":[{"code":"EUR","name":"Euro","symbol":"€"}],"languages":[{"iso639_1":"es","iso639_2":"spa","name":"Spanish","nativeName":"Español"}],"translations":{"de":"Spanien","es":"España","fr":"Espagne","ja":"スペイン","it":"Spagna","br":"Espanha","pt":"Espanha","nl":"Spanje","hr":"Španjolska","fa":"اسپانیا"},"flag":"https://restcountries.eu/data/esp.svg","regionalBlocs":[{"acronym":"EU","name":"European Union","otherAcronyms":[],"otherNames":[]}],"cioc":"ESP"},{"name":"Italy","topLevelDomain":[".it"],"alpha2Code":"IT","alpha3Code":"ITA","callingCodes":["39"],"capital":"Rome","altSpellings":["IT","Italian Republic","Repubblica italiana"],"region":"Europe","subregion":"Southern Europe","population":60665551,"latlng":[42.83333333,12.83333333],"demonym":"Italian","area":301336.0,"gini":36.0,"timezones":["UTC+01:00"],"borders":["AUT","FRA","SMR","SVN","CHE","VAT"],"nativeName":"Italia","numericCode":"380","currencies":[{"code":"EUR","name":"Euro","symbol":"€"}],"languages":[{"iso639_1":"it","iso639_2":"ita","name":"Italian","nativeName":"Italiano"}],"translations":{"de":"Italien","es":"Italia","fr":"Italie","ja":"イタリア","it":"Italia","br":"Itália","pt":"Itália","nl":"Italië","hr":"Italija","fa":"ایتالیا"},"flag":"https://restcountries.eu/data/ita.svg","regionalBlocs":[{"acronym":"EU","name":"European Union","otherAcronyms":[],"otherNames":[]}],"cioc":"ITA"},{"name":"Estonia","topLevelDomain":[".ee"],"alpha2Code":"EE","alpha3Code":"EST","callingCodes":["372"],"capital":"Tallinn","altSpellings":["EE","Eesti","Republic of Estonia","Eesti Vabariik"],"region":"Europe","subregion":"Northern Europe","population":1315944,"latlng":[59.0,26.0],"demonym":"Estonian","area":45227.0,"gini":36.0,"timezones":["UTC+02:00"],"borders":["LVA","RUS"],"nativeName":"Eesti","numericCode":"233","currencies":[{"code":"EUR","name":"Euro","symbol":"€"}],"languages":[{"iso639_1":"et","iso639_2":"est","name":"Estonian","nativeName":"eesti"}],"translations":{"de":"Estland","es":"Estonia","fr":"Estonie","ja":"エストニア","it":"Estonia","br":"Estônia","pt":"Estónia","nl":"Estland","hr":"Estonija","fa":"استونی"},"flag":"https://restcountries.eu/data/est.svg","regionalBlocs":[{"acronym":"EU","name":"European Union","otherAcronyms":[],"otherNames":[]}],"cioc":"EST"}]